interpreTS/__init__.py
interpreTS/core/__init__.py
interpreTS/core/feature_extractor.py
interpreTS/core/time_series_data.py
interpreTS/core/features/__init__.py
interpreTS/core/features/distance_to_the_last_change_point.py
interpreTS/core/features/feature_above_9th_decile.py
interpreTS/core/features/feature_absolute_energy.py
interpreTS/core/features/feature_amplitude_change_rate.py
interpreTS/core/features/feature_approximate_entropy.py
interpreTS/core/features/feature_below_1st_decile.py
interpreTS/core/features/feature_binarize_mean.py
interpreTS/core/features/feature_crossing_points.py
interpreTS/core/features/feature_distance_to_the_last_change_point.py
interpreTS/core/features/feature_entropy.py
interpreTS/core/features/feature_flat_spots.py
interpreTS/core/features/feature_heterogeneity.py
interpreTS/core/features/feature_histogram_dominant.py
interpreTS/core/features/feature_length.py
interpreTS/core/features/feature_linearity.py
interpreTS/core/features/feature_mean.py
interpreTS/core/features/feature_mean_change.py
interpreTS/core/features/feature_missing_points.py
interpreTS/core/features/feature_outliers_iqr.py
interpreTS/core/features/feature_outliers_std.py
interpreTS/core/features/feature_peak.py
interpreTS/core/features/feature_quantile.py
interpreTS/core/features/feature_seasonality_strength.py
interpreTS/core/features/feature_significant_changes.py
interpreTS/core/features/feature_spikeness.py
interpreTS/core/features/feature_stability.py
interpreTS/core/features/feature_std_1st_der.py
interpreTS/core/features/feature_trend_strength.py
interpreTS/core/features/feature_trough.py
interpreTS/core/features/feature_variability_in_sub_periods.py
interpreTS/core/features/feature_variance.py
interpreTS/core/features/feature_variance_change.py
interpreTS/core/features/histogram_dominant.py
interpreTS/core/features/mean_change.py
interpreTS/core/features/seasonality_strength.py
interpreTS/core/features/trend_strength.py
InterpreTS-0.5.0.dist-info/LICENSE
InterpreTS-0.5.0.dist-info/METADATA
InterpreTS-0.5.0.dist-info/WHEEL
InterpreTS-0.5.0.dist-info/top_level.txt
InterpreTS-0.5.0.dist-info/RECORD
