Metadata-Version: 2.1
Name: InterpreTS
Version: 0.5.0
Summary: Feature extraction from time series to support the creation of interpretable and explainable predictive models.
Home-page: https://github.com/ruleminer/InterpreTS
Author: ['Sławomir Put', 'Martyna Żur', 'Weronika Wołowczyk', 'Jarosław Strzelczyk', 'Piotr Krupiński', 'Martyna Kramarz', 'Łukasz Wróbel']
Project-URL: Documentation, https://github.com/ruleminer/InterpreTS/docs
Project-URL: Source, https://github.com/ruleminer/InterpreTS
Project-URL: Tracker, https://github.com/ruleminer/InterpreTS/issues
Keywords: time series feature extraction interpretability explainability machine learning
Classifier: Development Status :: 4 - Beta
Classifier: License :: OSI Approved :: GNU Affero General Public License v3
Classifier: Programming Language :: Python :: 3
Classifier: Operating System :: Microsoft :: Windows
Classifier: Operating System :: Unix
Classifier: Topic :: Scientific/Engineering
Classifier: Topic :: Scientific/Engineering :: Artificial Intelligence
Classifier: Intended Audience :: Developers
Classifier: Intended Audience :: Science/Research
Requires-Python: >=3.10
License-File: LICENSE
Requires-Dist: pandas==2.2.3
Requires-Dist: numpy
Requires-Dist: statsmodels==0.14.4
Requires-Dist: langchain-community==0.3.14
Requires-Dist: langchain==0.3.14
Requires-Dist: openai==1.59.4
Requires-Dist: streamlit==1.41.1
Requires-Dist: scikit-learn
Requires-Dist: joblib==1.4.2
Requires-Dist: tqdm==4.67.1
Requires-Dist: dask==2024.12.1
Requires-Dist: scipy==1.15.0
Requires-Dist: pillow==11.1.0
